dlu_voice_transcriber/__init__.py
dlu_voice_transcriber/__main__.py
dlu_voice_transcriber/core/__init__.py
dlu_voice_transcriber/core/recorder.py
dlu_voice_transcriber/core/transcriber.py
dlu_voice_transcriber-0.2.3.dist-info/LICENSE
dlu_voice_transcriber-0.2.3.dist-info/METADATA
dlu_voice_transcriber-0.2.3.dist-info/WHEEL
dlu_voice_transcriber-0.2.3.dist-info/entry_points.txt
dlu_voice_transcriber-0.2.3.dist-info/top_level.txt
dlu_voice_transcriber-0.2.3.dist-info/RECORD
