Metadata-Version: 2.1
Name: dlu_voice_transcriber
Version: 0.2.3
Summary: A multilingual voice recording and transcription tool with German and English support
Author-email: Dirk Ulbricht <dirk.ulbricht@gmail.com>
License: MIT
Project-URL: Homepage, https://github.com/dullibri/dlu_voice_transcriber
Project-URL: Bug Tracker, https://github.com/dullibri/dlu_voice_transcriber/issues
Project-URL: Documentation, https://github.com/dullibri/dlu_voice_transcriber#readme
Project-URL: Source Code, https://github.com/dullibri/dlu_voice_transcriber
Project-URL: Changelog, https://github.com/dullibri/dlu_voice_transcriber/blob/main/CHANGELOG.md
Keywords: audio recording,speech recognition,transcription,german transcription,voice to text,multilingual,audio processing
Classifier: Development Status :: 4 - Beta
Classifier: Programming Language :: Python :: 3
Classifier: Programming Language :: Python :: 3.8
Classifier: Programming Language :: Python :: 3.9
Classifier: Programming Language :: Python :: 3.10
Classifier: Programming Language :: Python :: 3.11
Classifier: License :: OSI Approved :: MIT License
Classifier: Operating System :: OS Independent
Classifier: Topic :: Multimedia :: Sound/Audio :: Speech
Classifier: Topic :: Multimedia :: Sound/Audio :: Capture/Recording
Classifier: Natural Language :: English
Classifier: Natural Language :: German
Classifier: Intended Audience :: Developers
Classifier: Intended Audience :: Education
Classifier: Intended Audience :: End Users/Desktop
Requires-Python: <3.12,>=3.8
License-File: LICENSE
Requires-Dist: pyaudio >=0.2.14
Requires-Dist: SpeechRecognition >=3.11.0
Requires-Dist: pydub >=0.25.1
Requires-Dist: wave >=0.0.2
